ntcore/__init__.py
ntcore/_logutil.py
ntcore/py.typed
ntcore/types.py
ntcore/util.py
ntcore/version.py
ntcore/meta/__init__.py
ntcore/src/NetworkTable.cpp.inl
ntcore/src/NetworkTableEntry.cpp.inl
ntcore/src/nt_instance.cpp
ntcore/src/nt_instance.h
ntcore/src/nt_type_caster.h
ntcore/src/ntcore.cpp
ntcore/src/py2value.cpp
ntcore/src/py2value.h
ntcore/src/pyentry.cpp
ntcore/src/pyentry.h
ntcore/_init__ntcore.py
ntcore/_ntcore.cp310-win_amd64.lib
ntcore/_ntcore.cp310-win_amd64.pyd
ntcore/ntcore.pc
ntcore/_ntcore/__init__.pyi
ntcore/_ntcore/meta.pyi
ntcore/trampolines/nt__BooleanArrayEntry.hpp
ntcore/trampolines/nt__BooleanArrayPublisher.hpp
ntcore/trampolines/nt__BooleanArraySubscriber.hpp
ntcore/trampolines/nt__BooleanArrayTopic.hpp
ntcore/trampolines/nt__BooleanEntry.hpp
ntcore/trampolines/nt__BooleanPublisher.hpp
ntcore/trampolines/nt__BooleanSubscriber.hpp
ntcore/trampolines/nt__BooleanTopic.hpp
ntcore/trampolines/nt__ConnectionInfo.hpp
ntcore/trampolines/nt__DoubleArrayEntry.hpp
ntcore/trampolines/nt__DoubleArrayPublisher.hpp
ntcore/trampolines/nt__DoubleArraySubscriber.hpp
ntcore/trampolines/nt__DoubleArrayTopic.hpp
ntcore/trampolines/nt__DoubleEntry.hpp
ntcore/trampolines/nt__DoublePublisher.hpp
ntcore/trampolines/nt__DoubleSubscriber.hpp
ntcore/trampolines/nt__DoubleTopic.hpp
ntcore/trampolines/nt__Event.hpp
ntcore/trampolines/nt__EventFlags.hpp
ntcore/trampolines/nt__FloatArrayEntry.hpp
ntcore/trampolines/nt__FloatArrayPublisher.hpp
ntcore/trampolines/nt__FloatArraySubscriber.hpp
ntcore/trampolines/nt__FloatArrayTopic.hpp
ntcore/trampolines/nt__FloatEntry.hpp
ntcore/trampolines/nt__FloatPublisher.hpp
ntcore/trampolines/nt__FloatSubscriber.hpp
ntcore/trampolines/nt__FloatTopic.hpp
ntcore/trampolines/nt__GenericEntry.hpp
ntcore/trampolines/nt__GenericPublisher.hpp
ntcore/trampolines/nt__GenericSubscriber.hpp
ntcore/trampolines/nt__IntegerArrayEntry.hpp
ntcore/trampolines/nt__IntegerArrayPublisher.hpp
ntcore/trampolines/nt__IntegerArraySubscriber.hpp
pyntcore-2025.3.2.3.dist-info/METADATA
pyntcore-2025.3.2.3.dist-info/WHEEL
pyntcore-2025.3.2.3.dist-info/entry_points.txt
pyntcore-2025.3.2.3.dist-info/RECORD
