Metadata-Version: 2.4
Name: pyntcore
Version: 2025.3.2.3
Summary: Binary wrappers for the FRC ntcore library
Project-URL: Source code, https://github.com/robotpy/mostrobotpy
Author-email: RobotPy Development Team <robotpy@googlegroups.com>
License-Expression: BSD-3-Clause
Requires-Dist: robotpy-native-ntcore==2025.3.2
Requires-Dist: robotpy-wpinet==2025.3.2.3
Requires-Dist: robotpy-wpiutil==2025.3.2.3
